qtoggleserver/startup.py
qtoggleserver/version.py
qtoggleserver/commands/__init__.py
qtoggleserver/commands/server.py
qtoggleserver/commands/shell.py
qtoggleserver/conf/__init__.py
qtoggleserver/conf/metadata.py
qtoggleserver/conf/settings.py
qtoggleserver/core/__init__.py
qtoggleserver/core/history.py
qtoggleserver/core/main.py
qtoggleserver/core/ports.py
qtoggleserver/core/responses.py
qtoggleserver/core/reverse.py
qtoggleserver/core/sequences.py
qtoggleserver/core/sessions.py
qtoggleserver/core/typing.py
qtoggleserver/core/vports.py
qtoggleserver/core/webhooks.py
qtoggleserver/core/api/__init__.py
qtoggleserver/core/api/auth.py
qtoggleserver/core/api/schema.py
qtoggleserver/core/api/funcs/__init__.py
qtoggleserver/core/api/funcs/backup.py
qtoggleserver/core/api/funcs/device.py
qtoggleserver/core/api/funcs/firmware.py
qtoggleserver/core/api/funcs/ports.py
qtoggleserver/core/api/funcs/reverse.py
qtoggleserver/core/api/funcs/various.py
qtoggleserver/core/api/funcs/webhooks.py
qtoggleserver/core/device/__init__.py
qtoggleserver/core/device/attrs.py
qtoggleserver/core/device/events.py
qtoggleserver/core/device/exceptions.py
qtoggleserver/core/events/__init__.py
qtoggleserver/core/events/base.py
qtoggleserver/core/events/device.py
qtoggleserver/core/events/handlers.py
qtoggleserver/core/events/port.py
qtoggleserver/core/expressions/__init__.py
qtoggleserver/core/expressions/aggregation.py
qtoggleserver/core/expressions/arithmetic.py
qtoggleserver/core/expressions/base.py
qtoggleserver/core/expressions/bitwise.py
qtoggleserver/core/expressions/branching.py
qtoggleserver/core/expressions/comparison.py
qtoggleserver/core/expressions/date.py
qtoggleserver/core/expressions/exceptions.py
qtoggleserver/core/expressions/functions.py
qtoggleserver/core/expressions/literalvalues.py
qtoggleserver/core/expressions/logic.py
qtoggleserver/core/expressions/ports.py
qtoggleserver/core/expressions/rounding.py
qtoggleserver/core/expressions/sign.py
qtoggleserver-0.30.1.dist-info/licenses/LICENSE.txt
qtoggleserver-0.30.1.dist-info/METADATA
qtoggleserver-0.30.1.dist-info/WHEEL
qtoggleserver-0.30.1.dist-info/entry_points.txt
qtoggleserver-0.30.1.dist-info/top_level.txt
qtoggleserver-0.30.1.dist-info/RECORD
