Metadata-Version: 2.4
Name: qtoggleserver
Version: 0.30.1
Summary: A fully fledged qToggle implementation written in Python
Author-email: Calin Crisan <ccrisan@gmail.com>
License: Apache 2.0
Requires-Python: >=3.11
License-File: LICENSE.txt
Requires-Dist: bleak<1,>=0.14
Requires-Dist: cachetools>=6.2.1
Requires-Dist: cachetools-async>=0.0.5
Requires-Dist: dbus-next<1,>=0.2
Requires-Dist: jinja2<4,>=3
Requires-Dist: jsonpointer<3,>=2.0
Requires-Dist: jsonschema<5,>=2.5
Requires-Dist: psutil<6,>=5.5
Requires-Dist: pyhocon<1,>=0.3.50
Requires-Dist: pyjwt<3,>=2
Requires-Dist: pytz
Requires-Dist: qui-server>=1.18
Requires-Dist: tornado<7,>=6.0
Provides-Extra: opt
Requires-Dist: asyncpg; extra == "opt"
Requires-Dist: pymongo; extra == "opt"
Requires-Dist: redis; extra == "opt"
Dynamic: license-file
